moviepy_cli/__init__.py
moviepy_cli-1.0.3.dist-info/METADATA
moviepy_cli-1.0.3.dist-info/WHEEL
moviepy_cli-1.0.3.dist-info/entry_points.txt
moviepy_cli-1.0.3.dist-info/RECORD
