Metadata-Version: 2.4
Name: moviepy-cli
Version: 1.0.3
Summary: Command line tools for quick video editing.
Project-URL: Homepage, http://github.com/wkentaro/moviepy-cli
Author-email: Kentaro Wada <www.kentaro.wada@gmail.com>
License-Expression: MIT
Classifier: Development Status :: 4 - Beta
Classifier: Environment :: Console
Classifier: Intended Audience :: Developers
Classifier: Operating System :: OS Independent
Classifier: Programming Language :: Python
Classifier: Programming Language :: Python :: 3 :: Only
Classifier: Programming Language :: Python :: 3.10
Classifier: Programming Language :: Python :: 3.11
Classifier: Programming Language :: Python :: 3.12
Classifier: Programming Language :: Python :: 3.13
Classifier: Programming Language :: Python :: 3.14
Requires-Python: >=3.10
Requires-Dist: moviepy<2
Requires-Dist: path<17
